automcp/__init__.py
automcp/cli.py
automcp/adapters/__init__.py
automcp/adapters/crewai.py
automcp/adapters/langgraph.py
automcp/adapters/llamaindex.py
automcp/adapters/mcp_agent.py
automcp/adapters/openai.py
automcp/adapters/pydantic.py
automcp/adapters/utils.py
automcp/cli_templates/framework_config.yaml
automcp/cli_templates/run_mcp.py.template
mseep_naptha_automcp-0.1.2.dist-info/METADATA
mseep_naptha_automcp-0.1.2.dist-info/WHEEL
mseep_naptha_automcp-0.1.2.dist-info/entry_points.txt
mseep_naptha_automcp-0.1.2.dist-info/licenses/LICENSE
mseep_naptha_automcp-0.1.2.dist-info/RECORD
